cardia/__init__.py
cardia/__main__.py
cardia-0.0.8.dist-info/METADATA
cardia-0.0.8.dist-info/WHEEL
cardia-0.0.8.dist-info/entry_points.txt
cardia-0.0.8.dist-info/top_level.txt
cardia-0.0.8.dist-info/RECORD
