Metadata-Version: 2.1
Name: cardia
Version: 0.0.8
Summary: Python library for intelligent code card generation.
Home-page: https://github.com/kevin91nl/cardia
Author: Kevin Jacobs
Author-email: mail@kevinjacobs.nl
License: MIT
Classifier: License :: OSI Approved :: MIT License
Classifier: Programming Language :: Python :: 3
Classifier: Programming Language :: Python :: 3.11
